MANIFEST.in
README.txt
setup.py
o2w/__init__.py
o2w/settings/__init__.py
o2w/settings/common.py
o2w/settings/dev.py
o2w/settings/helpers.py
o2w/settings/prod.py
o2w_settings.egg-info/PKG-INFO
o2w_settings.egg-info/SOURCES.txt
o2w_settings.egg-info/dependency_links.txt
o2w_settings.egg-info/top_level.txt