Metadata-Version: 1.0
Name: o2w-settings
Version: 0.0.1
Summary: Helper funcions
Home-page: http://www.o2w.es/
Author: José Sánchez Moreno
Author-email: jose@o2w.es
License: LICENSE.txt
Platform: UNKNOWN
